aiida_ase/__init__.py
aiida_ase/calculations/__init__.py
aiida_ase/calculations/ase.py
aiida_ase/parsers/__init__.py
aiida_ase/parsers/ase.py
aiida_ase/parsers/gpaw.py
aiida_ase/workflows/__init__.py
aiida_ase/workflows/base.py
aiida_ase-3.0.0.dist-info/entry_points.txt
aiida_ase-3.0.0.dist-info/LICENSE.txt
aiida_ase-3.0.0.dist-info/WHEEL
aiida_ase-3.0.0.dist-info/METADATA
aiida_ase-3.0.0.dist-info/RECORD
