Metadata-Version: 2.1
Name: aiida-ase
Version: 3.0.0
Summary: The official AiiDA plugin for ASE.
Keywords: aiida,workflows,ase
Author-email: The AiiDA team <developers@aiida.net>
Requires-Python: >=3.8
Classifier: Development Status :: 4 - Beta
Classifier: Framework :: AiiDA
Classifier: License :: OSI Approved :: MIT License
Classifier: Operating System :: POSIX :: Linux
Classifier: Operating System :: MacOS :: MacOS X
Classifier: Programming Language :: Python
Classifier: Programming Language :: Python :: 3.8
Classifier: Programming Language :: Python :: 3.9
Classifier: Programming Language :: Python :: 3.10
Classifier: Programming Language :: Python :: 3.11
Classifier: Topic :: Scientific/Engineering
Requires-Dist: aiida-core~=2.0
Requires-Dist: ase
Requires-Dist: sphinx ; extra == "docs"
Requires-Dist: sphinx-autoapi ; extra == "docs"
Requires-Dist: sphinx-book-theme ; extra == "docs"
Requires-Dist: sphinx-click ; extra == "docs"
Requires-Dist: sphinx-copybutton ; extra == "docs"
Requires-Dist: pre-commit ; extra == "pre-commit"
Requires-Dist: pylint ; extra == "pre-commit"
Requires-Dist: pgtest ; extra == "tests"
Requires-Dist: pytest ; extra == "tests"
Requires-Dist: pytest-regressions ; extra == "tests"
Project-URL: Source, https://github.com/aiidaplugins/aiida-ase
Provides-Extra: docs
Provides-Extra: pre-commit
Provides-Extra: tests
